coldfilms/__init__.py
coldfilms-0.1.7.dist-info/DESCRIPTION.rst
coldfilms-0.1.7.dist-info/METADATA
coldfilms-0.1.7.dist-info/RECORD
coldfilms-0.1.7.dist-info/WHEEL
coldfilms-0.1.7.dist-info/metadata.json
coldfilms-0.1.7.dist-info/top_level.txt
