Metadata-Version: 2.0
Name: coldfilms
Version: 0.1.7
Summary: A python API for icefilms
Home-page: https://git.steov.com/steov/coldfilms
Author: Steve Foley
Author-email: sfoley1988@gmail.com
License: GPLv2+
Download-URL: https://git.steov.com/steov/coldfilms/archive/v0.1.7.tar.gz
Platform: UNKNOWN
Classifier: Development Status :: 3 - Alpha
Classifier: License :: OSI Approved :: GNU General Public License v2 or later (GPLv2+)
Classifier: Intended Audience :: Developers
Classifier: Programming Language :: Python :: 3.4
Classifier: Programming Language :: Python :: 3.5
Classifier: Programming Language :: Python :: 3.6
Requires-Dist: steov
Requires-Dist: bs4
Requires-Dist: html5lib
